gpx_lite/__init__.py
gpx_lite/gpx.py
gpx_lite/gpxtrack.py
gpx_lite/gpxtrackpoint.py
gpx_lite/gpxtracksegment.py
gpx_lite/parser.py
gpx_lite/utils.py
gpx_lite-0.0.5.dist-info/METADATA
gpx_lite-0.0.5.dist-info/RECORD
gpx_lite-0.0.5.dist-info/WHEEL
gpx_lite-0.0.5.dist-info/top_level.txt
