Metadata-Version: 2.1
Name: gpx-lite
Version: 0.0.5
Summary: Simple parser for gpx tracks, segments, and points with latitude, longitude, and time.
Home-page: https://github.com/aicenter/gpx_lite
Author: Olga Kholkovskaia
Author-email: olga.kholkovskaia@gmail.com
License: Apache License, Version 2.0
Platform: UNKNOWN
Requires-Dist: typing (>=3.6.2)
Requires-Dist: tqdm
